kg26_excel_writer/__init__.py
kg26_excel_writer-0.2.0.dist-info/METADATA
kg26_excel_writer-0.2.0.dist-info/WHEEL
kg26_excel_writer-0.2.0.dist-info/top_level.txt
kg26_excel_writer-0.2.0.dist-info/RECORD
